sqlvault/__init__.py
sqlvault/base.py
sqlvault/memoize.py
sqlvault/serialize.py
sqlvault/vault.py
sqlvault-0.0.6.dist-info/licenses/LICENSE
tests/test_sqlvault.py
sqlvault-0.0.6.dist-info/METADATA
sqlvault-0.0.6.dist-info/WHEEL
sqlvault-0.0.6.dist-info/top_level.txt
sqlvault-0.0.6.dist-info/RECORD
