Metadata-Version: 2.4
Name: sqlvault
Version: 0.0.6
Summary: Simple SQL-based key/value store
Author-email: Peter Mirzoian <fragarie.dev@yandex.com>
License: MIT License
Classifier: Programming Language :: Python :: 3
Requires-Python: >=3.12
License-File: LICENSE
Requires-Dist: sqlalchemy>=2.0.0
Dynamic: license-file
